dotscanner/__init__.py
dotscanner/__main__.py
dotscanner/dataprocessing.py
dotscanner/density.py
dotscanner/files.py
dotscanner/lifetime.py
dotscanner/programtype.py
dotscanner/strings.py
dotscanner/ui/DefaultUserSettingsEditor.py
dotscanner/ui/DialogWindow.py
dotscanner/ui/MicroscopeImage.py
dotscanner/ui/RegionSelector.py
dotscanner/ui/ThresholdAdjuster.py
dotscanner/ui/UserSettings.py
dotscanner/ui/__init__.py
dotscanner/ui/window.py
settings/__init__.py
settings/config.py
settings/configmanagement.py
tests/__init__.py
tests/test_dataprocessing.py
tests/test_density.py
tests/test_files.py
tests/test_fullAnalysis.py
tests/test_lifetime.py
tests/test_strings.py
tests/data/__init__.py
tests/ui/FakeMicroscopeImage.py
tests/ui/FakeUserSettings.py
tests/ui/__init__.py
tests/ui/test_MicroscopeImage.py
tests/ui/test_ThresholdAdjuster.py
dotscanner-1.5.8.dist-info/LICENSE
dotscanner-1.5.8.dist-info/METADATA
dotscanner-1.5.8.dist-info/WHEEL
dotscanner-1.5.8.dist-info/entry_points.txt
dotscanner-1.5.8.dist-info/top_level.txt
dotscanner-1.5.8.dist-info/RECORD
