Metadata-Version: 2.1
Name: dotscanner
Version: 1.5.8
Summary: A program designed for analysis of microscope imaging data
Home-page: https://github.com/bdavis222/dotscanner
Author: Holly Allen and Brian Davis
Author-email: holly.allen@colorado.edu
License: MIT
Project-URL: Bug Reports, https://github.com/bdavis222/dotscanner/issues
Project-URL: Funding, https://www.paypal.com/donate/?business=UA5NL9MJSFMVY
Project-URL: Source, https://github.com/bdavis222/dotscanner
Classifier: Intended Audience :: Science/Research
Classifier: License :: OSI Approved :: MIT License
Classifier: Programming Language :: Python :: 3
Classifier: Operating System :: Unix
Classifier: Operating System :: MacOS :: MacOS X
Classifier: Operating System :: Microsoft :: Windows
Requires-Python: >=3.7, <4
License-File: LICENSE
Requires-Dist: matplotlib
Requires-Dist: numpy
